pywheat/__init__.py
pywheat/main.py
pywheat/data/__init__.py
pywheat/data/satellite.py
pywheat/data/config/.DS_Store
pywheat/data/config/configbycoords.cfg
pywheat/data/config/configbygenotype.cfg
pywheat/data/example/.DS_Store
pywheat/data/example/KSAS.WTH
pywheat/data/example/Meteo_data_Final_20221219.csv
pywheat/data/example/NDVI_Ave_Final_20221219.csv
pywheat/data/example/Pheno_Ave_Final_20221219.csv
pywheat/data/example/weather_Kansas_State_Univ_WaggerMG_1983.parquet
pywheat/data/whstages/.DS_Store
pywheat/data/whstages/stage_1.png
pywheat/data/whstages/stage_2.png
pywheat/data/whstages/stage_3.png
pywheat/data/whstages/stage_4.png
pywheat/data/whstages/stage_4a.png
pywheat/data/whstages/stage_5.png
pywheat/data/whstages/stage_6.png
pywheat/data/whstages/stage_7.png
pywheat/data/whstages/stage_8.png
pywheat/data/whstages/stage_9.png
pywheat/pheno/__init__.py
pywheat/pheno/phenology.py
pywheat/utils/__init__.py
pywheat/utils/metrics.py
pywheat-0.1.1.dist-info/LICENSE
pywheat-0.1.1.dist-info/METADATA
pywheat-0.1.1.dist-info/WHEEL
pywheat-0.1.1.dist-info/entry_points.txt
pywheat-0.1.1.dist-info/top_level.txt
pywheat-0.1.1.dist-info/RECORD
