Metadata-Version: 2.1
Name: pywheat
Version: 0.1.1
Summary: Python library for simulation of wheat phenological development, crop growth and yield at large scales
Home-page: https://github.com/egiron/pywheat
Author: Ernesto Giron Echeverry
Author-email: e.giron.e@gmail.com
License: GPLv3+
Project-URL: Issue Tracking, https://github.com/egiron/pywheat/issues
Keywords: wheat,crop modeling
Classifier: Development Status :: 4 - Beta
Classifier: Programming Language :: Python :: 3
Classifier: License :: Free for non-commercial use
Classifier: License :: OSI Approved :: GNU General Public License v3 or later (GPLv3+)
Classifier: Operating System :: OS Independent
Classifier: License :: Free for non-commercial use
Classifier: Environment :: Console
Classifier: Framework :: Jupyter
Classifier: Programming Language :: Python :: 3.9
Classifier: Programming Language :: Python :: 3.10
Classifier: Programming Language :: Python :: 3.11
Classifier: Intended Audience :: Developers
Classifier: Intended Audience :: Education
Classifier: Intended Audience :: End Users/Desktop
Classifier: Intended Audience :: Information Technology
Classifier: Intended Audience :: Science/Research
Requires-Python: >=3.9
License-File: LICENSE
Requires-Dist: numpy
Requires-Dist: numba
Requires-Dist: pandas
Requires-Dist: scikit-learn
Requires-Dist: scipy
Requires-Dist: tqdm
Requires-Dist: seaborn
Requires-Dist: Shapely
Requires-Dist: ipython
Requires-Dist: duckdb
Requires-Dist: pyarrow
Requires-Dist: click
